win_precise_time/__init__.py
win_precise_time/_t.c
win_precise_time/_t.cp38-win_amd64.pyd
win_precise_time/_t.pyi
win_precise_time/py.typed
win_precise_time-1.4.2.dist-info/LICENSE.txt
win_precise_time-1.4.2.dist-info/METADATA
win_precise_time-1.4.2.dist-info/WHEEL
win_precise_time-1.4.2.dist-info/top_level.txt
win_precise_time-1.4.2.dist-info/RECORD
