Metadata-Version: 2.1
Name: win-precise-time
Version: 1.4.2
Author-email: Artur Drogunow <artur.drogunow@zf.com>
License: MIT
Project-URL: Documentation, https://win-precise-time.readthedocs.io/en/latest/
Project-URL: Issues, https://github.com/zariiii9003/win-precise-time/issues
Project-URL: Source, https://github.com/zariiii9003/win-precise-time
Project-URL: Homepage, https://github.com/zariiii9003/win-precise-time
Keywords: Windows,time,sleep,GetSystemTimePreciseAsFileTime,SetWaitableTimerEx,CREATE_WAITABLE_TIMER_HIGH_RESOLUTION
Classifier: Development Status :: 5 - Production/Stable
Classifier: Programming Language :: Python
Classifier: Programming Language :: Python :: 3
Classifier: Programming Language :: Python :: Implementation :: CPython
Requires-Python: >=3.7
License-File: LICENSE.txt
